README.md
setup.py
librenms/__init__.py
librenms/librenms.py
librenms.egg-info/PKG-INFO
librenms.egg-info/SOURCES.txt
librenms.egg-info/dependency_links.txt
librenms.egg-info/requires.txt
librenms.egg-info/top_level.txt